mcworldtools/__init__.py
mcworldtools/main.py
mcworldtools/util.py
mcworldtools/tools/__init__.py
mcworldtools/tools/blocks.py
mcworldtools/tools/command_blocks.py
mcworldtools/tools/entities.py
mcworldtools/tools/remove_unused_chunks.py
mcworldtools-1.2.6.dist-info/LICENSE
mcworldtools-1.2.6.dist-info/METADATA
mcworldtools-1.2.6.dist-info/WHEEL
mcworldtools-1.2.6.dist-info/entry_points.txt
mcworldtools-1.2.6.dist-info/top_level.txt
mcworldtools-1.2.6.dist-info/RECORD
