Metadata-Version: 2.1
Name: mcworldtools
Version: 1.2.6
Summary: Useful tools for Minecraft worlds such as removing unused chunks and finding blocks, command blocks or entities.
Home-page: https://github.com/Rapha149/MCWorldTools
Author: Rapha149
License: GPL-3.0
Project-URL: Code, https://github.com/Rapha149/MCWorldTools
Project-URL: Issues, https://github.com/Rapha149/MCWorldTools
Keywords: minecraft,world,minecraft-world,nbt
Platform: UNKNOWN
Classifier: Topic :: Games/Entertainment
Classifier: Topic :: Utilities
Classifier: Development Status :: 4 - Beta
Classifier: License :: OSI Approved :: GNU General Public License v3 (GPLv3)
Classifier: Programming Language :: Python :: 3
Classifier: Programming Language :: Python :: 3.6
Classifier: Operating System :: OS Independent
Classifier: Environment :: Console
Classifier: Intended Audience :: End Users/Desktop
Classifier: Intended Audience :: System Administrators
Classifier: Natural Language :: English
Requires-Python: >=3.6
License-File: LICENSE
Requires-Dist: nbt (>=1.5.1)
Requires-Dist: pathlib
Requires-Dist: tqdm
Requires-Dist: argparse
Requires-Dist: pyyaml
Requires-Dist: regex
Requires-Dist: pyreadline
